{
    "formatVersion":  1,
    "benchmark":  "fabric-1.19.2-client-flow",
    "stage":  "world",
    "startedAtUtc":  "2026-07-15T00:52:35.7989387Z",
    "endpoint":  "http://127.0.0.1:37832/mcp",
    "records":  [
                    {
                        "operation":  "tool:ui_wait",
                        "input":  {
                                      "until":  "in_world",
                                      "pollIntervalMs":  100,
                                      "timeoutMs":  5000
                                  },
                        "expectation":  "wait for in_world",
                        "expectedStatuses":  [
                                                 "ok"
                                             ],
                        "expectedErrorCodes":  [

                                               ],
                        "asserted":  true,
                        "httpStatus":  200,
                        "status":  "ok",
                        "result":  {
                                       "pollCount":  1.0,
                                       "timedOut":  false,
                                       "state":  {
                                                     "capturedAtTick":  233.0,
                                                     "coverage":  "complete",
                                                     "guiScale":  2.0,
                                                     "height":  240.0,
                                                     "inWorld":  true,
                                                     "open":  false,
                                                     "screen":  "",
                                                     "screenClass":  "",
                                                     "screenToken":  "53cb5322-34f3-4a85-bfef-7662b1fdf72c",
                                                     "snapshotRevision":  "8d149fab7e515d597a00f9616a7e3b636da79a9ec8ccd40d8c85223e0423628f",
                                                     "title":  "",
                                                     "truncated":  false,
                                                     "truncationCauses":  [

                                                                          ],
                                                     "widgets":  [

                                                                 ],
                                                     "width":  427.0
                                                 },
                                       "waitedFor":  "in_world",
                                       "elapsedMs":  1.0
                                   },
                        "error":  null
                    },
                    {
                        "operation":  "capability:minecraft.player.state.read@1.0",
                        "input":  {
                                      "input":  {

                                                },
                                      "capabilityVersion":  "1.0",
                                      "capability":  "minecraft.player.state.read",
                                      "dryRun":  false
                                  },
                        "expectation":  "player-state baseline",
                        "expectedStatuses":  [
                                                 "ok"
                                             ],
                        "expectedErrorCodes":  [

                                               ],
                        "asserted":  true,
                        "httpStatus":  200,
                        "status":  "ok",
                        "result":  {
                                       "rotation":  {
                                                        "pitch":  0.0,
                                                        "yaw":  0.0
                                                    },
                                       "food":  20.0,
                                       "uuid":  "3a8a4803-5263-381c-9fa0-2dc262c021aa",
                                       "health":  20.0,
                                       "name":  "Player387",
                                       "selectedSlot":  0.0,
                                       "position":  {
                                                        "x":  -21.5,
                                                        "y":  110.0,
                                                        "z":  -37.5
                                                    },
                                       "dimension":  "minecraft:overworld"
                                   },
                        "error":  null
                    },
                    {
                        "operation":  "capability:minecraft.player.context.read@1.0",
                        "input":  {
                                      "input":  {
                                                    "reach":  4
                                                },
                                      "capabilityVersion":  "1.0",
                                      "capability":  "minecraft.player.context.read",
                                      "dryRun":  false
                                  },
                        "expectation":  "player context",
                        "expectedStatuses":  [
                                                 "ok"
                                             ],
                        "expectedErrorCodes":  [

                                               ],
                        "asserted":  true,
                        "httpStatus":  200,
                        "status":  "ok",
                        "result":  {
                                       "blockPosition":  {
                                                             "x":  -22.0,
                                                             "y":  110.0,
                                                             "z":  -38.0
                                                         },
                                       "target":  {
                                                      "distance":  4.0,
                                                      "kind":  "miss",
                                                      "position":  {
                                                                       "x":  -21.5,
                                                                       "y":  111.62000000476837,
                                                                       "z":  -33.5
                                                                   },
                                                      "reach":  4.0
                                                  },
                                       "facing":  "south",
                                       "onGround":  true,
                                       "heldItem":  {
                                                        "count":  0.0,
                                                        "id":  "minecraft:air"
                                                    },
                                       "flying":  false,
                                       "dimension":  "minecraft:overworld",
                                       "gameMode":  "survival",
                                       "lookVector":  {
                                                          "x":  0.0,
                                                          "y":  0.0,
                                                          "z":  1.0
                                                      },
                                       "eyePosition":  {
                                                           "x":  -21.5,
                                                           "y":  111.62000000476837,
                                                           "z":  -37.5
                                                       },
                                       "position":  {
                                                        "x":  -21.5,
                                                        "y":  110.0,
                                                        "z":  -37.5
                                                    },
                                       "rotation":  {
                                                        "pitch":  0.0,
                                                        "yaw":  0.0
                                                    }
                                   },
                        "error":  null
                    },
                    {
                        "operation":  "capability:minecraft.server.info.read@1.0",
                        "input":  {
                                      "input":  {

                                                },
                                      "capabilityVersion":  "1.0",
                                      "capability":  "minecraft.server.info.read",
                                      "dryRun":  false
                                  },
                        "expectation":  "integrated-server info",
                        "expectedStatuses":  [
                                                 "ok"
                                             ],
                        "expectedErrorCodes":  [

                                               ],
                        "asserted":  true,
                        "httpStatus":  200,
                        "status":  "ok",
                        "result":  {
                                       "integratedServer":  true,
                                       "loader":  "fabric",
                                       "environment":  "integrated-server",
                                       "truncated":  false,
                                       "gameTime":  237.0,
                                       "gameVersion":  "1.19.2",
                                       "players":  [
                                                       {
                                                           "local":  true,
                                                           "name":  "Player387",
                                                           "uuid":  "3a8a4803-5263-381c-9fa0-2dc262c021aa"
                                                       }
                                                   ],
                                       "connected":  true,
                                       "playerCount":  1.0,
                                       "dimension":  "minecraft:overworld",
                                       "difficulty":  "normal",
                                       "dayTime":  237.0
                                   },
                        "error":  null
                    },
                    {
                        "operation":  "capability:minecraft.registry.item.search@1.0",
                        "input":  {
                                      "input":  {
                                                    "query":  "diamond",
                                                    "namespace":  "minecraft",
                                                    "limit":  3
                                                },
                                      "capabilityVersion":  "1.0",
                                      "capability":  "minecraft.registry.item.search",
                                      "dryRun":  false
                                  },
                        "expectation":  "registry read",
                        "expectedStatuses":  [
                                                 "ok"
                                             ],
                        "expectedErrorCodes":  [

                                               ],
                        "asserted":  true,
                        "httpStatus":  200,
                        "status":  "ok",
                        "result":  {
                                       "truncated":  true,
                                       "query":  "diamond",
                                       "items":  [
                                                     {
                                                         "blockItem":  false,
                                                         "displayName":  "Diamond",
                                                         "id":  "minecraft:diamond",
                                                         "maxStackSize":  64.0,
                                                         "translationKey":  "item.minecraft.diamond"
                                                     },
                                                     {
                                                         "blockItem":  false,
                                                         "displayName":  "Diamond Axe",
                                                         "id":  "minecraft:diamond_axe",
                                                         "maxStackSize":  1.0,
                                                         "translationKey":  "item.minecraft.diamond_axe"
                                                     },
                                                     {
                                                         "blockItem":  true,
                                                         "displayName":  "Block of Diamond",
                                                         "id":  "minecraft:diamond_block",
                                                         "maxStackSize":  64.0,
                                                         "translationKey":  "block.minecraft.diamond_block"
                                                     }
                                                 ],
                                       "limit":  3.0,
                                       "count":  3.0
                                   },
                        "error":  null
                    },
                    {
                        "operation":  "capability:minecraft.inventory.read@1.0",
                        "input":  {
                                      "input":  {

                                                },
                                      "capabilityVersion":  "1.0",
                                      "capability":  "minecraft.inventory.read",
                                      "dryRun":  false
                                  },
                        "expectation":  "inventory read",
                        "expectedStatuses":  [
                                                 "ok"
                                             ],
                        "expectedErrorCodes":  [

                                               ],
                        "asserted":  true,
                        "httpStatus":  200,
                        "status":  "ok",
                        "result":  {
                                       "slots":  [
                                                     {
                                                         "count":  0.0,
                                                         "empty":  true,
                                                         "item":  "minecraft:air",
                                                         "slot":  0.0
                                                     },
                                                     {
                                                         "count":  0.0,
                                                         "empty":  true,
                                                         "item":  "minecraft:air",
                                                         "slot":  1.0
                                                     },
                                                     {
                                                         "count":  0.0,
                                                         "empty":  true,
                                                         "item":  "minecraft:air",
                                                         "slot":  2.0
                                                     },
                                                     {
                                                         "count":  0.0,
                                                         "empty":  true,
                                                         "item":  "minecraft:air",
                                                         "slot":  3.0
                                                     },
                                                     {
                                                         "count":  0.0,
                                                         "empty":  true,
                                                         "item":  "minecraft:air",
                                                         "slot":  4.0
                                                     },
                                                     {
                                                         "count":  0.0,
                                                         "empty":  true,
                                                         "item":  "minecraft:air",
                                                         "slot":  5.0
                                                     },
                                                     {
                                                         "count":  0.0,
                                                         "empty":  true,
                                                         "item":  "minecraft:air",
                                                         "slot":  6.0
                                                     },
                                                     {
                                                         "count":  0.0,
                                                         "empty":  true,
                                                         "item":  "minecraft:air",
                                                         "slot":  7.0
                                                     },
                                                     {
                                                         "count":  0.0,
                                                         "empty":  true,
                                                         "item":  "minecraft:air",
                                                         "slot":  8.0
                                                     },
                                                     {
                                                         "count":  0.0,
                                                         "empty":  true,
                                                         "item":  "minecraft:air",
                                                         "slot":  9.0
                                                     },
                                                     {
                                                         "count":  0.0,
                                                         "empty":  true,
                                                         "item":  "minecraft:air",
                                                         "slot":  10.0
                                                     },
                                                     {
                                                         "count":  0.0,
                                                         "empty":  true,
                                                         "item":  "minecraft:air",
                                                         "slot":  11.0
                                                     },
                                                     {
                                                         "count":  0.0,
                                                         "empty":  true,
                                                         "item":  "minecraft:air",
                                                         "slot":  12.0
                                                     },
                                                     {
                                                         "count":  0.0,
                                                         "empty":  true,
                                                         "item":  "minecraft:air",
                                                         "slot":  13.0
                                                     },
                                                     {
                                                         "count":  0.0,
                                                         "empty":  true,
                                                         "item":  "minecraft:air",
                                                         "slot":  14.0
                                                     },
                                                     {
                                                         "count":  0.0,
                                                         "empty":  true,
                                                         "item":  "minecraft:air",
                                                         "slot":  15.0
                                                     },
                                                     {
                                                         "count":  0.0,
                                                         "empty":  true,
                                                         "item":  "minecraft:air",
                                                         "slot":  16.0
                                                     },
                                                     {
                                                         "count":  0.0,
                                                         "empty":  true,
                                                         "item":  "minecraft:air",
                                                         "slot":  17.0
                                                     },
                                                     {
                                                         "count":  0.0,
                                                         "empty":  true,
                                                         "item":  "minecraft:air",
                                                         "slot":  18.0
                                                     },
                                                     {
                                                         "count":  0.0,
                                                         "empty":  true,
                                                         "item":  "minecraft:air",
                                                         "slot":  19.0
                                                     },
                                                     {
                                                         "count":  0.0,
                                                         "empty":  true,
                                                         "item":  "minecraft:air",
                                                         "slot":  20.0
                                                     },
                                                     {
                                                         "count":  0.0,
                                                         "empty":  true,
                                                         "item":  "minecraft:air",
                                                         "slot":  21.0
                                                     },
                                                     {
                                                         "count":  0.0,
                                                         "empty":  true,
                                                         "item":  "minecraft:air",
                                                         "slot":  22.0
                                                     },
                                                     {
                                                         "count":  0.0,
                                                         "empty":  true,
                                                         "item":  "minecraft:air",
                                                         "slot":  23.0
                                                     },
                                                     {
                                                         "count":  0.0,
                                                         "empty":  true,
                                                         "item":  "minecraft:air",
                                                         "slot":  24.0
                                                     },
                                                     {
                                                         "count":  0.0,
                                                         "empty":  true,
                                                         "item":  "minecraft:air",
                                                         "slot":  25.0
                                                     },
                                                     {
                                                         "count":  0.0,
                                                         "empty":  true,
                                                         "item":  "minecraft:air",
                                                         "slot":  26.0
                                                     },
                                                     {
                                                         "count":  0.0,
                                                         "empty":  true,
                                                         "item":  "minecraft:air",
                                                         "slot":  27.0
                                                     },
                                                     {
                                                         "count":  0.0,
                                                         "empty":  true,
                                                         "item":  "minecraft:air",
                                                         "slot":  28.0
                                                     },
                                                     {
                                                         "count":  0.0,
                                                         "empty":  true,
                                                         "item":  "minecraft:air",
                                                         "slot":  29.0
                                                     },
                                                     {
                                                         "count":  0.0,
                                                         "empty":  true,
                                                         "item":  "minecraft:air",
                                                         "slot":  30.0
                                                     },
                                                     {
                                                         "count":  0.0,
                                                         "empty":  true,
                                                         "item":  "minecraft:air",
                                                         "slot":  31.0
                                                     },
                                                     {
                                                         "count":  0.0,
                                                         "empty":  true,
                                                         "item":  "minecraft:air",
                                                         "slot":  32.0
                                                     },
                                                     {
                                                         "count":  0.0,
                                                         "empty":  true,
                                                         "item":  "minecraft:air",
                                                         "slot":  33.0
                                                     },
                                                     {
                                                         "count":  0.0,
                                                         "empty":  true,
                                                         "item":  "minecraft:air",
                                                         "slot":  34.0
                                                     },
                                                     {
                                                         "count":  0.0,
                                                         "empty":  true,
                                                         "item":  "minecraft:air",
                                                         "slot":  35.0
                                                     },
                                                     {
                                                         "count":  0.0,
                                                         "empty":  true,
                                                         "item":  "minecraft:air",
                                                         "slot":  36.0
                                                     },
                                                     {
                                                         "count":  0.0,
                                                         "empty":  true,
                                                         "item":  "minecraft:air",
                                                         "slot":  37.0
                                                     },
                                                     {
                                                         "count":  0.0,
                                                         "empty":  true,
                                                         "item":  "minecraft:air",
                                                         "slot":  38.0
                                                     },
                                                     {
                                                         "count":  0.0,
                                                         "empty":  true,
                                                         "item":  "minecraft:air",
                                                         "slot":  39.0
                                                     },
                                                     {
                                                         "count":  0.0,
                                                         "empty":  true,
                                                         "item":  "minecraft:air",
                                                         "slot":  40.0
                                                     }
                                                 ],
                                       "selectedSlot":  0.0,
                                       "player":  {
                                                      "name":  "Player387",
                                                      "uuid":  "3a8a4803-5263-381c-9fa0-2dc262c021aa"
                                                  }
                                   },
                        "error":  null
                    },
                    {
                        "operation":  "capability:minecraft.entity.list@1.0",
                        "input":  {
                                      "input":  {
                                                    "includePlayers":  true,
                                                    "limit":  8
                                                },
                                      "capabilityVersion":  "1.0",
                                      "capability":  "minecraft.entity.list",
                                      "dryRun":  false
                                  },
                        "expectation":  "entity list",
                        "expectedStatuses":  [
                                                 "ok"
                                             ],
                        "expectedErrorCodes":  [

                                               ],
                        "asserted":  true,
                        "httpStatus":  200,
                        "status":  "ok",
                        "result":  {
                                       "entities":  [
                                                        {
                                                            "alive":  true,
                                                            "name":  "Donkey",
                                                            "onGround":  true,
                                                            "position":  {
                                                                             "x":  -20.749854845133036,
                                                                             "y":  109.0,
                                                                             "z":  -34.85830839138694
                                                                         },
                                                            "rotation":  {
                                                                             "pitch":  0.0,
                                                                             "yaw":  289.72186279296875
                                                                         },
                                                            "type":  "minecraft:donkey",
                                                            "uuid":  "41c4d58e-b06e-4456-9e5d-28a07826f7bf"
                                                        },
                                                        {
                                                            "alive":  true,
                                                            "name":  "Donkey",
                                                            "onGround":  true,
                                                            "position":  {
                                                                             "x":  -21.922952532023135,
                                                                             "y":  109.0,
                                                                             "z":  -34.729213636419026
                                                                         },
                                                            "rotation":  {
                                                                             "pitch":  0.0,
                                                                             "yaw":  306.25103759765625
                                                                         },
                                                            "type":  "minecraft:donkey",
                                                            "uuid":  "b57b4a1f-49e2-417c-87e5-1f812018dc41"
                                                        },
                                                        {
                                                            "alive":  true,
                                                            "name":  "Sheep",
                                                            "onGround":  true,
                                                            "position":  {
                                                                             "x":  -43.446577428190835,
                                                                             "y":  107.0,
                                                                             "z":  -12.548296192055268
                                                                         },
                                                            "rotation":  {
                                                                             "pitch":  0.0,
                                                                             "yaw":  47.88848876953125
                                                                         },
                                                            "type":  "minecraft:sheep",
                                                            "uuid":  "60d98802-d891-461a-8e2b-e799135f346b"
                                                        },
                                                        {
                                                            "alive":  true,
                                                            "name":  "Rabbit",
                                                            "onGround":  true,
                                                            "position":  {
                                                                             "x":  -15.599999994039536,
                                                                             "y":  111.0,
                                                                             "z":  -127.59999999403954
                                                                         },
                                                            "rotation":  {
                                                                             "pitch":  0.0,
                                                                             "yaw":  353.02978515625
                                                                         },
                                                            "type":  "minecraft:rabbit",
                                                            "uuid":  "5acd9758-bb6d-4cc1-8b02-bbd833bbe623"
                                                        },
                                                        {
                                                            "alive":  true,
                                                            "name":  "Chicken",
                                                            "onGround":  true,
                                                            "position":  {
                                                                             "x":  27.0,
                                                                             "y":  96.0,
                                                                             "z":  47.0
                                                                         },
                                                            "rotation":  {
                                                                             "pitch":  0.0,
                                                                             "yaw":  60.326229095458984
                                                                         },
                                                            "type":  "minecraft:chicken",
                                                            "uuid":  "fd3990f1-818e-4aa9-bc6a-c79e74934ce0"
                                                        },
                                                        {
                                                            "alive":  true,
                                                            "name":  "Pig",
                                                            "onGround":  true,
                                                            "position":  {
                                                                             "x":  -67.52500445017782,
                                                                             "y":  89.0,
                                                                             "z":  53.2416048433435
                                                                         },
                                                            "rotation":  {
                                                                             "pitch":  0.0,
                                                                             "yaw":  357.6094970703125
                                                                         },
                                                            "type":  "minecraft:pig",
                                                            "uuid":  "10fd435b-835d-400e-a622-f6fc4c3c7b5f"
                                                        },
                                                        {
                                                            "alive":  true,
                                                            "name":  "Sheep",
                                                            "onGround":  true,
                                                            "position":  {
                                                                             "x":  -70.81359056487176,
                                                                             "y":  103.0,
                                                                             "z":  61.252496291328534
                                                                         },
                                                            "rotation":  {
                                                                             "pitch":  0.0,
                                                                             "yaw":  308.21087646484375
                                                                         },
                                                            "type":  "minecraft:sheep",
                                                            "uuid":  "2f14b5fa-481a-4940-90f9-fb2986cc385a"
                                                        },
                                                        {
                                                            "alive":  true,
                                                            "name":  "Sheep",
                                                            "onGround":  true,
                                                            "position":  {
                                                                             "x":  16.899999976158142,
                                                                             "y":  104.0,
                                                                             "z":  -142.0
                                                                         },
                                                            "rotation":  {
                                                                             "pitch":  0.0,
                                                                             "yaw":  247.37445068359375
                                                                         },
                                                            "type":  "minecraft:sheep",
                                                            "uuid":  "4d1c54ba-7d01-43c6-92a1-3b343320bb53"
                                                        }
                                                    ],
                                       "truncated":  true,
                                       "dimension":  "minecraft:overworld",
                                       "limit":  8.0
                                   },
                        "error":  null
                    },
                    {
                        "operation":  "capability:minecraft.entity.nearby.read@1.0",
                        "input":  {
                                      "input":  {
                                                    "radius":  8,
                                                    "includePlayers":  true,
                                                    "limit":  8
                                                },
                                      "capabilityVersion":  "1.0",
                                      "capability":  "minecraft.entity.nearby.read",
                                      "dryRun":  false
                                  },
                        "expectation":  "nearby entities",
                        "expectedStatuses":  [
                                                 "ok"
                                             ],
                        "expectedErrorCodes":  [

                                               ],
                        "asserted":  true,
                        "httpStatus":  200,
                        "status":  "ok",
                        "result":  {
                                       "truncated":  false,
                                       "radius":  8.0,
                                       "limit":  8.0,
                                       "entities":  [
                                                        {
                                                            "distance":  2.9221401196317216,
                                                            "entityId":  3.0,
                                                            "name":  "Donkey",
                                                            "player":  false,
                                                            "position":  {
                                                                             "x":  -20.750244140625,
                                                                             "y":  109.0,
                                                                             "z":  -34.858642578125
                                                                         },
                                                            "type":  "minecraft:donkey",
                                                            "uuid":  "41c4d58e-b06e-4456-9e5d-28a07826f7bf"
                                                        },
                                                        {
                                                            "distance":  3.0277108542068003,
                                                            "entityId":  4.0,
                                                            "name":  "Donkey",
                                                            "player":  false,
                                                            "position":  {
                                                                             "x":  -22.014892578125,
                                                                             "y":  109.0,
                                                                             "z":  -34.68896484375
                                                                         },
                                                            "type":  "minecraft:donkey",
                                                            "uuid":  "b57b4a1f-49e2-417c-87e5-1f812018dc41"
                                                        }
                                                    ],
                                       "dimension":  "minecraft:overworld"
                                   },
                        "error":  null
                    },
                    {
                        "operation":  "capability:minecraft.world.heightmap.read@1.0",
                        "input":  {
                                      "input":  {
                                                    "sizeX":  2,
                                                    "sizeZ":  2,
                                                    "includeSurfaceBlocks":  true,
                                                    "z":  -38,
                                                    "x":  -22
                                                },
                                      "capabilityVersion":  "1.0",
                                      "capability":  "minecraft.world.heightmap.read",
                                      "dryRun":  false
                                  },
                        "expectation":  "heightmap read",
                        "expectedStatuses":  [
                                                 "ok"
                                             ],
                        "expectedErrorCodes":  null,
                        "asserted":  true,
                        "httpStatus":  200,
                        "status":  "ok",
                        "result":  {
                                       "size":  {
                                                    "x":  2.0,
                                                    "z":  2.0
                                                },
                                       "unloadedColumns":  0.0,
                                       "stats":  {
                                                     "hasHeightData":  true,
                                                     "heightRange":  1.0,
                                                     "maxHeight":  109.0,
                                                     "minHeight":  108.0
                                                 },
                                       "columns":  [
                                                       {
                                                           "empty":  false,
                                                           "height":  109.0,
                                                           "loaded":  true,
                                                           "surfaceBlock":  "minecraft:grass_block",
                                                           "x":  -22.0,
                                                           "z":  -38.0
                                                       },
                                                       {
                                                           "empty":  false,
                                                           "height":  109.0,
                                                           "loaded":  true,
                                                           "surfaceBlock":  "minecraft:grass_block",
                                                           "x":  -21.0,
                                                           "z":  -38.0
                                                       },
                                                       {
                                                           "empty":  false,
                                                           "height":  108.0,
                                                           "loaded":  true,
                                                           "surfaceBlock":  "minecraft:grass_block",
                                                           "x":  -22.0,
                                                           "z":  -37.0
                                                       },
                                                       {
                                                           "empty":  false,
                                                           "height":  109.0,
                                                           "loaded":  true,
                                                           "surfaceBlock":  "minecraft:grass_block",
                                                           "x":  -21.0,
                                                           "z":  -37.0
                                                       }
                                                   ],
                                       "columnCount":  4.0,
                                       "loadedColumns":  4.0,
                                       "origin":  {
                                                      "x":  -22.0,
                                                      "z":  -38.0
                                                  },
                                       "dimension":  "minecraft:overworld"
                                   },
                        "error":  null
                    },
                    {
                        "operation":  "capability:minecraft.world.light.analyze@1.0",
                        "input":  {
                                      "input":  {
                                                    "y":  110,
                                                    "sizeY":  2,
                                                    "x":  -22,
                                                    "darkSpotLimit":  4,
                                                    "sizeX":  2,
                                                    "sizeZ":  2,
                                                    "lightSourceLimit":  4,
                                                    "resolution":  1,
                                                    "z":  -38
                                                },
                                      "capabilityVersion":  "1.0",
                                      "capability":  "minecraft.world.light.analyze",
                                      "dryRun":  false
                                  },
                        "expectation":  "light analysis",
                        "expectedStatuses":  [
                                                 "ok"
                                             ],
                        "expectedErrorCodes":  null,
                        "asserted":  true,
                        "httpStatus":  200,
                        "status":  "ok",
                        "result":  {
                                       "distribution":  {
                                                            "dark":  {
                                                                         "count":  0.0,
                                                                         "percentage":  0.0
                                                                     },
                                                            "dim":  {
                                                                        "count":  0.0,
                                                                        "percentage":  0.0
                                                                    },
                                                            "wellLit":  {
                                                                            "count":  8.0,
                                                                            "percentage":  100.0
                                                                        }
                                                        },
                                       "analyzedSamples":  8.0,
                                       "mobSpawnRisk":  "none",
                                       "solidSamples":  0.0,
                                       "histogram":  [
                                                         0.0,
                                                         0.0,
                                                         0.0,
                                                         0.0,
                                                         0.0,
                                                         0.0,
                                                         0.0,
                                                         0.0,
                                                         0.0,
                                                         0.0,
                                                         0.0,
                                                         0.0,
                                                         0.0,
                                                         0.0,
                                                         0.0,
                                                         8.0
                                                     ],
                                       "resolution":  1.0,
                                       "dimension":  "minecraft:overworld",
                                       "darkSpotCount":  0.0,
                                       "unloadedSamples":  0.0,
                                       "lightSources":  [

                                                        ],
                                       "darkSpotsTruncated":  false,
                                       "darkSpots":  [

                                                     ],
                                       "lightSourceCount":  0.0,
                                       "size":  {
                                                    "x":  2.0,
                                                    "y":  2.0,
                                                    "z":  2.0
                                                },
                                       "averageCombinedLight":  15.0,
                                       "candidateSamples":  8.0,
                                       "origin":  {
                                                      "x":  -22.0,
                                                      "y":  110.0,
                                                      "z":  -38.0
                                                  },
                                       "lightSourcesTruncated":  false,
                                       "suggestions":  [

                                                       ]
                                   },
                        "error":  null
                    },
                    {
                        "operation":  "capability:minecraft.world.blocks.read@1.0",
                        "input":  {
                                      "input":  {
                                                    "sizeZ":  1,
                                                    "y":  113,
                                                    "dimension":  "minecraft:overworld",
                                                    "z":  -38,
                                                    "x":  -22,
                                                    "sizeX":  1,
                                                    "sizeY":  1
                                                },
                                      "capabilityVersion":  "1.0",
                                      "capability":  "minecraft.world.blocks.read",
                                      "dryRun":  false
                                  },
                        "expectation":  "block baseline read",
                        "expectedStatuses":  [
                                                 "ok"
                                             ],
                        "expectedErrorCodes":  [

                                               ],
                        "asserted":  true,
                        "httpStatus":  200,
                        "status":  "ok",
                        "result":  {
                                       "size":  {
                                                    "x":  1.0,
                                                    "y":  1.0,
                                                    "z":  1.0
                                                },
                                       "origin":  {
                                                      "x":  -22.0,
                                                      "y":  113.0,
                                                      "z":  -38.0
                                                  },
                                       "dimension":  "minecraft:overworld",
                                       "count":  1.0,
                                       "blocks":  [
                                                      {
                                                          "air":  true,
                                                          "block":  "minecraft:air",
                                                          "loaded":  true,
                                                          "position":  {
                                                                           "x":  -22.0,
                                                                           "y":  113.0,
                                                                           "z":  -38.0
                                                                       }
                                                      }
                                                  ]
                                   },
                        "error":  null
                    },
                    {
                        "operation":  "capability:minecraft.world.blocks.read@1.0",
                        "input":  {
                                      "input":  {
                                                    "sizeZ":  1,
                                                    "y":  114,
                                                    "dimension":  "minecraft:overworld",
                                                    "z":  -38,
                                                    "x":  -22,
                                                    "sizeX":  1,
                                                    "sizeY":  1
                                                },
                                      "capabilityVersion":  "1.0",
                                      "capability":  "minecraft.world.blocks.read",
                                      "dryRun":  false
                                  },
                        "expectation":  "mutation target baseline read",
                        "expectedStatuses":  [
                                                 "ok"
                                             ],
                        "expectedErrorCodes":  [

                                               ],
                        "asserted":  true,
                        "httpStatus":  200,
                        "status":  "ok",
                        "result":  {
                                       "size":  {
                                                    "x":  1.0,
                                                    "y":  1.0,
                                                    "z":  1.0
                                                },
                                       "origin":  {
                                                      "x":  -22.0,
                                                      "y":  114.0,
                                                      "z":  -38.0
                                                  },
                                       "dimension":  "minecraft:overworld",
                                       "count":  1.0,
                                       "blocks":  [
                                                      {
                                                          "air":  true,
                                                          "block":  "minecraft:air",
                                                          "loaded":  true,
                                                          "position":  {
                                                                           "x":  -22.0,
                                                                           "y":  114.0,
                                                                           "z":  -38.0
                                                                       }
                                                      }
                                                  ]
                                   },
                        "error":  null
                    },
                    {
                        "operation":  "capability:minecraft.world.blocks.write@1.0",
                        "input":  {
                                      "input":  {
                                                    "changes":  [
                                                                    {
                                                                        "y":  114,
                                                                        "block":  "minecraft:air",
                                                                        "z":  -38,
                                                                        "x":  -22
                                                                    }
                                                                ],
                                                    "dimension":  "minecraft:overworld",
                                                    "dryRun":  false
                                                },
                                      "capabilityVersion":  "1.0",
                                      "capability":  "minecraft.world.blocks.write",
                                      "dryRun":  true
                                  },
                        "expectation":  "validate reversible mutation",
                        "expectedStatuses":  [
                                                 "ok"
                                             ],
                        "expectedErrorCodes":  [

                                               ],
                        "asserted":  true,
                        "httpStatus":  200,
                        "status":  "ok",
                        "result":  {
                                       "dimension":  "minecraft:overworld",
                                       "validated":  true,
                                       "requestedCount":  1.0,
                                       "dryRun":  true,
                                       "changes":  [
                                                       {
                                                           "applied":  false,
                                                           "changed":  true,
                                                           "position":  {
                                                                            "x":  -22.0,
                                                                            "y":  114.0,
                                                                            "z":  -38.0
                                                                        },
                                                           "previousBlock":  "minecraft:air",
                                                           "requestedBlock":  "minecraft:gold_block"
                                                       }
                                                   ],
                                       "changedCount":  0.0
                                   },
                        "error":  null
                    },
                    {
                        "operation":  "capability:minecraft.world.blocks.write@1.0",
                        "input":  {
                                      "input":  {
                                                    "changes":  [
                                                                    {
                                                                        "y":  114,
                                                                        "block":  "minecraft:air",
                                                                        "z":  -38,
                                                                        "x":  -22
                                                                    }
                                                                ],
                                                    "dimension":  "minecraft:overworld",
                                                    "dryRun":  false
                                                },
                                      "capabilityVersion":  "1.0",
                                      "capability":  "minecraft.world.blocks.write",
                                      "dryRun":  false
                                  },
                        "expectation":  "write marker block",
                        "expectedStatuses":  [
                                                 "ok"
                                             ],
                        "expectedErrorCodes":  [

                                               ],
                        "asserted":  true,
                        "httpStatus":  200,
                        "status":  "ok",
                        "result":  {
                                       "dimension":  "minecraft:overworld",
                                       "validated":  true,
                                       "requestedCount":  1.0,
                                       "dryRun":  false,
                                       "changes":  [
                                                       {
                                                           "applied":  true,
                                                           "changed":  true,
                                                           "position":  {
                                                                            "x":  -22.0,
                                                                            "y":  114.0,
                                                                            "z":  -38.0
                                                                        },
                                                           "previousBlock":  "minecraft:air",
                                                           "requestedBlock":  "minecraft:gold_block"
                                                       }
                                                   ],
                                       "changedCount":  1.0
                                   },
                        "error":  null
                    },
                    {
                        "operation":  "capability:minecraft.world.blocks.read@1.0",
                        "input":  {
                                      "input":  {
                                                    "sizeZ":  1,
                                                    "y":  114,
                                                    "dimension":  "minecraft:overworld",
                                                    "z":  -38,
                                                    "x":  -22,
                                                    "sizeX":  1,
                                                    "sizeY":  1
                                                },
                                      "capabilityVersion":  "1.0",
                                      "capability":  "minecraft.world.blocks.read",
                                      "dryRun":  false
                                  },
                        "expectation":  "marker readback",
                        "expectedStatuses":  [
                                                 "ok"
                                             ],
                        "expectedErrorCodes":  [

                                               ],
                        "asserted":  true,
                        "httpStatus":  200,
                        "status":  "ok",
                        "result":  {
                                       "size":  {
                                                    "x":  1.0,
                                                    "y":  1.0,
                                                    "z":  1.0
                                                },
                                       "origin":  {
                                                      "x":  -22.0,
                                                      "y":  114.0,
                                                      "z":  -38.0
                                                  },
                                       "dimension":  "minecraft:overworld",
                                       "count":  1.0,
                                       "blocks":  [
                                                      {
                                                          "air":  false,
                                                          "block":  "minecraft:gold_block",
                                                          "loaded":  true,
                                                          "position":  {
                                                                           "x":  -22.0,
                                                                           "y":  114.0,
                                                                           "z":  -38.0
                                                                       }
                                                      }
                                                  ]
                                   },
                        "error":  null
                    },
                    {
                        "operation":  "capability:minecraft.world.blocks.write@1.0",
                        "input":  {
                                      "input":  {
                                                    "changes":  [
                                                                    {
                                                                        "y":  114,
                                                                        "block":  "minecraft:air",
                                                                        "z":  -38,
                                                                        "x":  -22
                                                                    }
                                                                ],
                                                    "dimension":  "minecraft:overworld",
                                                    "dryRun":  false
                                                },
                                      "capabilityVersion":  "1.0",
                                      "capability":  "minecraft.world.blocks.write",
                                      "dryRun":  false
                                  },
                        "expectation":  "restore marker location",
                        "expectedStatuses":  [
                                                 "ok"
                                             ],
                        "expectedErrorCodes":  [

                                               ],
                        "asserted":  true,
                        "httpStatus":  200,
                        "status":  "ok",
                        "result":  {
                                       "dimension":  "minecraft:overworld",
                                       "validated":  true,
                                       "requestedCount":  1.0,
                                       "dryRun":  false,
                                       "changes":  [
                                                       {
                                                           "applied":  true,
                                                           "changed":  true,
                                                           "position":  {
                                                                            "x":  -22.0,
                                                                            "y":  114.0,
                                                                            "z":  -38.0
                                                                        },
                                                           "previousBlock":  "minecraft:gold_block",
                                                           "requestedBlock":  "minecraft:air"
                                                       }
                                                   ],
                                       "changedCount":  1.0
                                   },
                        "error":  null
                    },
                    {
                        "operation":  "capability:minecraft.world.blocks.read@1.0",
                        "input":  {
                                      "input":  {
                                                    "sizeZ":  1,
                                                    "y":  114,
                                                    "dimension":  "minecraft:overworld",
                                                    "z":  -38,
                                                    "x":  -22,
                                                    "sizeX":  1,
                                                    "sizeY":  1
                                                },
                                      "capabilityVersion":  "1.0",
                                      "capability":  "minecraft.world.blocks.read",
                                      "dryRun":  false
                                  },
                        "expectation":  "restoration readback",
                        "expectedStatuses":  [
                                                 "ok"
                                             ],
                        "expectedErrorCodes":  [

                                               ],
                        "asserted":  true,
                        "httpStatus":  200,
                        "status":  "ok",
                        "result":  {
                                       "size":  {
                                                    "x":  1.0,
                                                    "y":  1.0,
                                                    "z":  1.0
                                                },
                                       "origin":  {
                                                      "x":  -22.0,
                                                      "y":  114.0,
                                                      "z":  -38.0
                                                  },
                                       "dimension":  "minecraft:overworld",
                                       "count":  1.0,
                                       "blocks":  [
                                                      {
                                                          "air":  true,
                                                          "block":  "minecraft:air",
                                                          "loaded":  true,
                                                          "position":  {
                                                                           "x":  -22.0,
                                                                           "y":  114.0,
                                                                           "z":  -38.0
                                                                       }
                                                      }
                                                  ]
                                   },
                        "error":  null
                    },
                    {
                        "operation":  "capability:minecraft.player.look@1.0",
                        "input":  {
                                      "input":  {
                                                    "pitch":  0,
                                                    "yaw":  1
                                                },
                                      "capabilityVersion":  "1.0",
                                      "capability":  "minecraft.player.look",
                                      "dryRun":  false
                                  },
                        "expectation":  "rotate one degree",
                        "expectedStatuses":  [
                                                 "ok"
                                             ],
                        "expectedErrorCodes":  [

                                               ],
                        "asserted":  true,
                        "httpStatus":  200,
                        "status":  "ok",
                        "result":  {
                                       "pitch":  0.0,
                                       "yaw":  1.0
                                   },
                        "error":  null
                    },
                    {
                        "operation":  "capability:minecraft.player.state.read@1.0",
                        "input":  {
                                      "input":  {

                                                },
                                      "capabilityVersion":  "1.0",
                                      "capability":  "minecraft.player.state.read",
                                      "dryRun":  false
                                  },
                        "expectation":  "rotation readback",
                        "expectedStatuses":  [
                                                 "ok"
                                             ],
                        "expectedErrorCodes":  [

                                               ],
                        "asserted":  true,
                        "httpStatus":  200,
                        "status":  "ok",
                        "result":  {
                                       "rotation":  {
                                                        "pitch":  0.0,
                                                        "yaw":  1.0
                                                    },
                                       "food":  20.0,
                                       "uuid":  "3a8a4803-5263-381c-9fa0-2dc262c021aa",
                                       "health":  20.0,
                                       "name":  "Player387",
                                       "selectedSlot":  0.0,
                                       "position":  {
                                                        "x":  -21.5,
                                                        "y":  110.0,
                                                        "z":  -37.5
                                                    },
                                       "dimension":  "minecraft:overworld"
                                   },
                        "error":  null
                    },
                    {
                        "operation":  "capability:minecraft.player.look@1.0",
                        "input":  {
                                      "input":  {
                                                    "pitch":  0,
                                                    "yaw":  0
                                                },
                                      "capabilityVersion":  "1.0",
                                      "capability":  "minecraft.player.look",
                                      "dryRun":  false
                                  },
                        "expectation":  "restore rotation",
                        "expectedStatuses":  [
                                                 "ok"
                                             ],
                        "expectedErrorCodes":  [

                                               ],
                        "asserted":  true,
                        "httpStatus":  200,
                        "status":  "ok",
                        "result":  {
                                       "pitch":  0.0,
                                       "yaw":  0.0
                                   },
                        "error":  null
                    },
                    {
                        "operation":  "capability:minecraft.player.move@2.0",
                        "input":  {
                                      "input":  {
                                                    "jump":  false,
                                                    "sneak":  false,
                                                    "sprint":  false,
                                                    "forward":  0,
                                                    "strafe":  0,
                                                    "durationMs":  1
                                                },
                                      "capabilityVersion":  "2.0",
                                      "capability":  "minecraft.player.move",
                                      "dryRun":  false
                                  },
                        "expectation":  "zero-motion control path",
                        "expectedStatuses":  [
                                                 "ok"
                                             ],
                        "expectedErrorCodes":  null,
                        "asserted":  true,
                        "httpStatus":  200,
                        "status":  "ok",
                        "result":  {
                                       "strafe":  0.0,
                                       "sprint":  false,
                                       "jump":  false,
                                       "sneak":  false,
                                       "durationMs":  1.0,
                                       "forward":  0.0,
                                       "leaseGeneration":  2.0
                                   },
                        "error":  null
                    },
                    {
                        "operation":  "capability:minecraft.inventory.slot.select@1.0",
                        "input":  {
                                      "input":  {
                                                    "slot":  0
                                                },
                                      "capabilityVersion":  "1.0",
                                      "capability":  "minecraft.inventory.slot.select",
                                      "dryRun":  false
                                  },
                        "expectation":  "reselect current slot",
                        "expectedStatuses":  [
                                                 "ok"
                                             ],
                        "expectedErrorCodes":  null,
                        "asserted":  true,
                        "httpStatus":  200,
                        "status":  "ok",
                        "result":  {
                                       "selectedSlot":  0.0
                                   },
                        "error":  null
                    },
                    {
                        "operation":  "capability:minecraft.chat.send@1.0",
                        "input":  {
                                      "input":  {
                                                    "message":  "[Lodestone] Fabric 1.19.2 flow benchmark marker"
                                                },
                                      "capabilityVersion":  "1.0",
                                      "capability":  "minecraft.chat.send",
                                      "dryRun":  false
                                  },
                        "expectation":  "chat mutation/readback marker",
                        "expectedStatuses":  [
                                                 "ok"
                                             ],
                        "expectedErrorCodes":  [

                                               ],
                        "asserted":  true,
                        "httpStatus":  200,
                        "status":  "ok",
                        "result":  {
                                       "sent":  true,
                                       "recipientCount":  1.0,
                                       "message":  "[Lodestone] Fabric 1.19.2 flow benchmark marker"
                                   },
                        "error":  null
                    },
                    {
                        "operation":  "capability:minecraft.chat.read@1.0",
                        "input":  {
                                      "input":  {
                                                    "limit":  8
                                                },
                                      "capabilityVersion":  "1.0",
                                      "capability":  "minecraft.chat.read",
                                      "dryRun":  false
                                  },
                        "expectation":  "chat readback",
                        "expectedStatuses":  [
                                                 "ok"
                                             ],
                        "expectedErrorCodes":  [
                                                   "CAPABILITY_UNAVAILABLE"
                                               ],
                        "asserted":  true,
                        "httpStatus":  200,
                        "status":  "error",
                        "result":  {

                                   },
                        "error":  {
                                      "code":  "CAPABILITY_UNAVAILABLE",
                                      "message":  "This operation is not implemented by the Fabric 1.19.2 adapter yet.",
                                      "retryable":  false,
                                      "details":  {

                                                  }
                                  }
                    },
                    {
                        "operation":  "capability:minecraft.client.screenshot.capture@1.0",
                        "input":  {
                                      "input":  {
                                                    "maxWidth":  320,
                                                    "maxHeight":  180
                                                },
                                      "capabilityVersion":  "1.0",
                                      "capability":  "minecraft.client.screenshot.capture",
                                      "dryRun":  false
                                  },
                        "expectation":  "in-world capture",
                        "expectedStatuses":  [
                                                 "ok"
                                             ],
                        "expectedErrorCodes":  [

                                               ],
                        "asserted":  true,
                        "httpStatus":  200,
                        "status":  "ok",
                        "result":  {
                                       "originalHeight":  480.0,
                                       "artifact":  {
                                                        "sha256":  "41d1a10b7984a2f6146a8130d82cb26fe8b265d121dadb50415671a37b53e1c3",
                                                        "uri":  "lodestone://artifacts/sha256/41d1a10b7984a2f6146a8130d82cb26fe8b265d121dadb50415671a37b53e1c3",
                                                        "expiresAtEpochMs":  1784076819352,
                                                        "sizeBytes":  102365,
                                                        "mediaType":  "image/png"
                                                    },
                                       "width":  320.0,
                                       "playerPosition":  {
                                                              "x":  -21.5,
                                                              "y":  110.0,
                                                              "z":  -37.5
                                                          },
                                       "originalWidth":  854.0,
                                       "height":  179.0,
                                       "playerRotation":  {
                                                              "pitch":  0.0,
                                                              "yaw":  0.0
                                                          }
                                   },
                        "error":  null
                    },
                    {
                        "operation":  "capability:minecraft.input.release-all@1.0",
                        "input":  {
                                      "input":  {

                                                },
                                      "capabilityVersion":  "1.0",
                                      "capability":  "minecraft.input.release-all",
                                      "dryRun":  false
                                  },
                        "expectation":  "world input cleanup",
                        "expectedStatuses":  [
                                                 "ok"
                                             ],
                        "expectedErrorCodes":  [

                                               ],
                        "asserted":  true,
                        "httpStatus":  200,
                        "status":  "ok",
                        "result":  {
                                       "leaseGeneration":  3.0,
                                       "released":  [

                                                    ],
                                       "count":  0.0
                                   },
                        "error":  null
                    },
                    {
                        "operation":  "tool:ui_state",
                        "input":  {

                                  },
                        "expectation":  "live UI snapshot",
                        "expectedStatuses":  [
                                                 "ok"
                                             ],
                        "expectedErrorCodes":  [

                                               ],
                        "asserted":  true,
                        "httpStatus":  200,
                        "status":  "ok",
                        "result":  {
                                       "title":  "",
                                       "coverage":  "complete",
                                       "width":  427.0,
                                       "capturedAtTick":  282.0,
                                       "truncationCauses":  [

                                                            ],
                                       "widgets":  [

                                                   ],
                                       "screenToken":  "53cb5322-34f3-4a85-bfef-7662b1fdf72c",
                                       "screen":  "",
                                       "inWorld":  true,
                                       "guiScale":  2.0,
                                       "height":  240.0,
                                       "snapshotRevision":  "8d149fab7e515d597a00f9616a7e3b636da79a9ec8ccd40d8c85223e0423628f",
                                       "screenClass":  "",
                                       "open":  false,
                                       "truncated":  false
                                   },
                        "error":  null
                    }
                ],
    "provenance":  {
                       "sourceCommit":  "088f59ee78c901ca21c9411880ceee789fc0ac9b",
                       "sourceDirtyPaths":  [
                                                " M hosts/fabric/1.18.2/src/client/java/dev/lodestone/fabric/FabricClientController.java",
                                                " M hosts/fabric/1.19.2/src/client/java/dev/lodestone/fabric/FabricClientController.java",
                                                " M verification/assemble-v1-release.ps1",
                                                " M verification/neoforge-keepfocus-flow-benchmark.ps1"
                                            ],
                       "lodestoneArtifact":  {
                                                 "path":  "C:\\SyncedProjects\\Game Development\\Minecraft\\Mods\\Lodestone\\hosts\\fabric\\1.19.2\\build\\libs\\lodestone-1.0.0.jar",
                                                 "bytes":  431967,
                                                 "sha256":  "61dd917922393c3e8eb367cfc601407b4216496b72ee0af0fe0709bb4fcea9c2"
                                             }
                   },
    "sessionId":  "da95c8dc-8163-4007-8e24-7e8de61aef2f",
    "completedAtUtc":  "2026-07-15T00:52:39.4140127Z"
}
